{
    "$help": "https://aka.ms/terminal-documentation",
    "$schema": "https://aka.ms/terminal-profiles-schema",
    "actions": 
    [
        {
            "command": "paste",
            "keys": "ctrl+v"
        },
        {
            "command": 
            {
                "action": "copy",
                "singleLine": false
            },
            "keys": "ctrl+c"
        },
        {
            "command": "unbound",
            "keys": "alt+space"
        },
        {
            "command": "unbound",
            "keys": "ctrl+comma"
        },
        {
            "command": 
            {
                "action": "splitPane",
                "split": "auto",
                "splitMode": "duplicate"
            },
            "keys": "alt+shift+d"
        },
        {
            "command": "find",
            "keys": "ctrl+shift+f"
        }
    ],
    "confirmCloseAllTabs": false,
    "copyFormatting": "none",
    "copyOnSelect": false,
    "defaultProfile": "{e5a83caa-4c73-52b3-ae6b-bc438d721ef9}",
    "launchMode": "maximized",
    "newTabMenu": 
    [
        {
            "type": "remainingProfiles"
        }
    ],
    "profiles": 
    {
        "defaults": 
        {
            "colorScheme": "Tokyo Night",
            "font": 
            {
                "face": "JetBrainsMono Nerd Font",
                "size": 12.0,
                "weight": "normal"
            },
            "padding": "0",
            "scrollbarState": "hidden",
            "startingDirectory": null
        },
        "list": 
        [
            {
                "guid": "{e5a83caa-4c73-52b3-ae6b-bc438d721ef9}",
                "hidden": false,
                "name": "Ubuntu 22.04.3 LTS",
                "source": "CanonicalGroupLimited.Ubuntu22.04LTS_79rhkp1fndgsc"
            },
            {
                "guid": "{61c54bbd-c2c6-5271-96e7-009a87ff44bf}",
                "hidden": false,
                "name": "Windows PowerShell",
                "startingDirectory": "D:\\1Myprojects\\Programming\\Web"
            },
            {
                "guid": "{0caa0dad-35be-5f56-a8ff-afceeeaa6101}",
                "hidden": false,
                "name": "Command Line"
            }
        ]
    },
    "schemes": 
    [
        {
            "background": "#1B1E28",
            "black": "#1B1E28",
            "blue": "#DDFFFF",
            "brightBlack": "#ACCDFF",
            "brightBlue": "#D7FFFF",
            "brightCyan": "#D7FFFF",
            "brightGreen": "#E4C7FF",
            "brightPurple": "#C5E9FF",
            "brightRed": "#679DFF",
            "brightWhite": "#FFFFFF",
            "brightYellow": "#FAC2FF",
            "cursorColor": "#4F525D",
            "cyan": "#DDFFFF",
            "foreground": "#FFFFFF",
            "green": "#E4C7FF",
            "name": "Poimandres",
            "purple": "#C5E9FF",
            "red": "#679DFF",
            "selectionBackground": "#7CB424",
            "white": "#FFFFFF",
            "yellow": "#FAC2FF"
        },
        {
            "background": "#1A1B26",
            "black": "#414868",
            "blue": "#7AA2F7",
            "brightBlack": "#414868",
            "brightBlue": "#7AA2F7",
            "brightCyan": "#7DCFFF",
            "brightGreen": "#73DACA",
            "brightPurple": "#BB9AF7",
            "brightRed": "#F7768E",
            "brightWhite": "#C0CAF5",
            "brightYellow": "#E0AF68",
            "cursorColor": "#C0CAF5",
            "cyan": "#7DCFFF",
            "foreground": "#A9B1DC",
            "green": "#73DACA",
            "name": "Tokyo Night",
            "purple": "#BB9AF7",
            "red": "#F7768E",
            "selectionBackground": "#28344A",
            "white": "#C0CAF5",
            "yellow": "#E0AF68"
        },
    ],
    "themes": [],
    "useAcrylicInTabRow": true
}
